consigue/readme_consigue.py
consigue-1.0.dist-info/METADATA
consigue-1.0.dist-info/WHEEL
consigue-1.0.dist-info/license.txt
consigue-1.0.dist-info/top_level.txt
consigue-1.0.dist-info/RECORD
