Metadata-Version: 2.1
Name: consigue
Version: 1.0
Summary: Tratamiento de Datos mediante fases de procesos
Author: El Señor es el único eterno. Que la ciencia lo honre a Él.
Author-email: from.colombia.to.all@gmail.com
License: Mozilla Public License 2.0 (MPL 2.0)
Classifier: Programming Language :: Python :: 3
Classifier: License :: OSI Approved :: Mozilla Public License 2.0 (MPL 2.0)
Requires-Python: >=3.11.3
License-File: license.txt
